ipush/__init__.py
ipush/provider/__init__.py
ipush/provider/_provider.py
ipush/provider/alertzy.py
ipush/provider/bark.py
ipush/provider/chanify.py
ipush/provider/dingtalk.py
ipush/provider/feishu.py
ipush/provider/juhe.py
ipush/provider/lark.py
ipush/provider/notify.py
ipush/provider/pushdeer.py
ipush/provider/pushplus.py
ipush/provider/showdoc.py
ipush/provider/telegram.py
ipush/provider/wecom.py
ipush/provider/xizhi.py
ipush/utils/fetch.py
ipush/utils/helper.py
ipush-0.6.0.dist-info/METADATA
ipush-0.6.0.dist-info/WHEEL
ipush-0.6.0.dist-info/licenses/LICENSE
ipush-0.6.0.dist-info/RECORD
