Metadata-Version: 2.1
Name: ipush
Version: 0.6.0
Summary: 向 APP、微信平台推送通知。支持 Telegram、钉钉群、飞书群、企业微信群、Lark 群、Bark 等平台。
Project-URL: Homepage, https://git.jetsung.com/idev/pypush
Project-URL: Documentation, https://pypush.skiy.net/
Project-URL: Repository, https://github.com/idevsig/pypush
Project-URL: Download, https://github.com/idevsig/pypush/releases
Author-email: Jetsung Chan <jetsungchan@gmail.com>
License-File: LICENSE
Keywords: bark,chanify,dingtalk,feishu,lark,notify,push,pushdeer,pushplus,showdoc,telegram,wechat,xizhi
Classifier: Development Status :: 4 - Beta
Classifier: Environment :: Console
Classifier: Environment :: Web Environment
Classifier: Intended Audience :: Developers
Classifier: License :: OSI Approved :: Apache Software License
Classifier: Natural Language :: Chinese (Simplified)
Classifier: Operating System :: OS Independent
Classifier: Programming Language :: Python
Classifier: Programming Language :: Python :: 3
Classifier: Programming Language :: Python :: 3 :: Only
Classifier: Programming Language :: Python :: 3.8
Classifier: Programming Language :: Python :: 3.9
Classifier: Programming Language :: Python :: 3.10
Classifier: Programming Language :: Python :: 3.11
Classifier: Programming Language :: Python :: 3.12
Classifier: Programming Language :: Python :: Implementation :: CPython
Classifier: Topic :: Communications :: Email
Classifier: Topic :: Software Development :: Libraries
Requires-Python: >=3.8
Requires-Dist: lxml>=4.9.4
Requires-Dist: requests>=2.31.0
